{
  "primary_datacenter": "us-central1",
  "server": false,
  "encrypt:" "DtJ2A/Yn1yxhBL3kC5YIwY6aEUYm7OMhAtAHK3/QxsM=",
  "verify_incoming": false,
  "verify_outgoing": true,
  "verify_server_hostname": true,
  "ca_file": "consul-agent-ca.pem",
  "auto_encrypt": {
    "tls": true
  },
  "acl": {
    "enabled": true,
    "default_policy": "allow",
    "enable_token_persistence": true,
    "tokens": {
      "master": "6f4d67b1-ab8e-8d23-c130-52f7444de08f"
    }
  },
  "ports": {
    "grpc": 8502
  }

}
